konfchanger.py
konfchanger_utils.py
konfchanger-0.2.dist-info/LICENCE.txt
konfchanger-0.2.dist-info/METADATA
konfchanger-0.2.dist-info/WHEEL
konfchanger-0.2.dist-info/entry_points.txt
konfchanger-0.2.dist-info/top_level.txt
konfchanger-0.2.dist-info/RECORD
