Metadata-Version: 2.1
Name: konfchanger
Version: 0.2
Summary: A CLI tool to backup/restore configuration files
Home-page: https://github.com/SB-Jr/konfigchanger
Author: Shrijit Basak(SB-Jr)
Author-email: shrijitbasak@gmail.com
License: UNKNOWN
Keywords: backup restore configuration config files
Platform: UNKNOWN
Classifier: Programming Language :: Python :: 3.7
Classifier: License :: OSI Approved :: GNU General Public License v3 or later (GPLv3+)
Classifier: Operating System :: POSIX :: Linux
Requires-Python: >=3.7.7
Requires-Dist: Click
